[
  {
    "head": "Боевой дикий облик",
    "type": 1,
    "level": 2,
    "discription": [
      {
        "Item1": 1,
        "Item2": "Вы можете использовать умение «Дикий облик» бонусным действием, а не действием."
      },
      {
        "Item1": 1,
        "Item2": "Кроме того, пока вы перевоплощены умением «Дикий облик», вы можете бонусным действием потратить ячейку заклинания, чтобы восстановить 1к8 хитов за каждый уровень потраченной ячейки."
      }
    ]
  },
  {
    "head": "Облик круга",
    "type": 1,
    "level": 2,
    "discription": [
      {
        "Item1": 1,
        "Item2": "Обряды круга луны позволяют принимать облик более опасных животных. Вы можете превращаться в Зверя с показателем опасности до 1 (игнорируйте столбец «Макс. ПО» таблицы «Облик животного»)."
      },
      {
        "Item1": 1,
        "Item2": "Начиная с 6-го уровня, вы можете превращаться в Зверя с показателем опасности вплоть до уровня друида, поделённого на 3 (округляя в меньшую сторону)."
      }
    ]
  },
  {
    "head": "Природный удар",
    "type": 1,
    "level": 6,
    "discription": [
      {
        "Item1": 1,
        "Item2": "Ваши атаки в облике Зверя считаются магическими для преодоления сопротивления и иммунитета к немагическим атакам и урону."
      }
    ]
  },
  {
    "head": "Стихийный дикий облик",
    "type": 1,
    "level": 10,
    "discription": [
      {
        "Item1": 1,
        "Item2": "Вы можете потратить сразу два использования «Дикого облика», чтобы принять облик водяного, воздушного, земляного или огненного элементаля."
      }
    ]
  },
  {
    "head": "Тысяча лиц",
    "type": 1,
    "level": 14,
    "discription": [
      {
        "Item1": 1,
        "Item2": "Вы понимаете, как магически изменять детали своего облика. Вы можете неограниченно накладывать заклинание смена обличья."
      }
    ]
  }
]